{"noiseKey":{"private":{"type":"Buffer","data":"WDpOHpxdARRMjOjeIT16G3TZ6GaeljqGB5elMBiqV2Y="},"public":{"type":"Buffer","data":"dF5S4Ky7ywlUmotD6dBMopr8Rtu/7tLeSQCP4D6582w="}},"pairingEphemeralKeyPair":{"private":{"type":"Buffer","data":"gJSkCDJosY4WZ+pzsuUJTPI9Q1Oh3j7uEib7G+plAXY="},"public":{"type":"Buffer","data":"5mkzXNrAXyPCqLI3fdVrNdDozj4t4o4pWFzEQ2x80h8="}},"signedIdentityKey":{"private":{"type":"Buffer","data":"+E8Whaz1s28pf1jflt61WaD95aBjO8QDHBSrha0xWXI="},"public":{"type":"Buffer","data":"kuUY7rnDQbhUWM3eJTlJ00Eb7NevShaqiS1zmaHnUyM="}},"signedPreKey":{"keyPair":{"private":{"type":"Buffer","data":"wHapTxOxNrub0j14lv1ZO/OT+lVd2Pf1v8ZvE4AeQlA="},"public":{"type":"Buffer","data":"ioW20kSP09sH5CUQI4octC+/ul/J8StAkf0DQcxH3m4="}},"signature":{"type":"Buffer","data":"zvoH58ctR3R4bzctaerK8bmd+IhjMJtAPA8UYo0pEwvxfLsdGsAfTnzRF1kc0jxTuKMvIqK8MgZiPihjoWeoiQ=="},"keyId":1},"registrationId":239,"advSecretKey":"0Pt8kvpwdFuHoB834ipQjILBG4TpOMR86ts+4Pi22CI=","processedHistoryMessages":[{"key":{"remoteJid":"6288292081326@s.whatsapp.net","fromMe":false,"id":"AC5F39D2F521AD2760DAE4331021B6A8","participant":"","addressingMode":"pn"},"messageTimestamp":1781078186},{"key":{"remoteJid":"6288292081326@s.whatsapp.net","fromMe":false,"id":"AC64433496313C11452906EF981D79D8","participant":"","addressingMode":"pn"},"messageTimestamp":1781078186},{"key":{"remoteJid":"6288292081326@s.whatsapp.net","fromMe":false,"id":"AC523CF809171024004F7338CF65EE2A","participant":"","addressingMode":"pn"},"messageTimestamp":1781078187},{"key":{"remoteJid":"6288292081326@s.whatsapp.net","fromMe":false,"id":"ACA9D3EFF77265F9C2418F291C5BA1E3","participant":"","addressingMode":"pn"},"messageTimestamp":1781078188},{"key":{"remoteJid":"6288292081326@s.whatsapp.net","fromMe":false,"id":"AC6354050EFDB74760F9851137A08F1A","participant":"","addressingMode":"pn"},"messageTimestamp":1781078269},{"key":{"remoteJid":"6288292081326@s.whatsapp.net","fromMe":false,"id":"AC8FA2CF74A81F76796BEC75469B5375","participant":"","addressingMode":"pn"},"messageTimestamp":1781078291},{"key":{"remoteJid":"6288292081326@s.whatsapp.net","fromMe":false,"id":"ACBCCB947A2436B0014491F63B4BE3B8","participant":"","addressingMode":"pn"},"messageTimestamp":1781078552},{"key":{"remoteJid":"6288292081326@s.whatsapp.net","fromMe":false,"id":"AC4BF9016C4A417B63B5511FE07B85C1","participant":"","addressingMode":"pn"},"messageTimestamp":1781078552},{"key":{"remoteJid":"6288292081326@s.whatsapp.net","fromMe":false,"id":"AC91FBF3C15055A7D866D0FF3DE83BE0","participant":"","addressingMode":"pn"},"messageTimestamp":1781078553},{"key":{"remoteJid":"6288292081326@s.whatsapp.net","fromMe":false,"id":"AC6B2BE4520E4575D86C96ECE6BE0349","participant":"","addressingMode":"pn"},"messageTimestamp":1781078553},{"key":{"remoteJid":"6288292081326@s.whatsapp.net","fromMe":false,"id":"AC5CC3B57B650351D736264B0265364E","participant":"","addressingMode":"pn"},"messageTimestamp":1781078553},{"key":{"remoteJid":"6288292081326@s.whatsapp.net","fromMe":false,"id":"ACBF70D102FA36AA824E24A423D615F8","participant":"","addressingMode":"pn"},"messageTimestamp":1781078578},{"key":{"remoteJid":"6288292081326@s.whatsapp.net","fromMe":false,"id":"AC7296C75D2BD5AA7A49C3866389AB8A","participant":"","addressingMode":"pn"},"messageTimestamp":1781078583},{"key":{"remoteJid":"6288292081326@s.whatsapp.net","fromMe":false,"id":"ACB708E4752315CAA4C4B2C1985CDD0C","participant":"","addressingMode":"pn"},"messageTimestamp":1781078643},{"key":{"remoteJid":"6288292081326@s.whatsapp.net","fromMe":false,"id":"AC5FAC533600E23F84156827A9648D94","participant":"","addressingMode":"pn"},"messageTimestamp":1781078648}],"nextPreKeyId":813,"firstUnuploadedPreKeyId":813,"accountSyncCounter":1,"accountSettings":{"unarchiveChats":false},"registered":false,"account":{"details":"CLX4imIQlLGk0QYYAyAAKAA=","accountSignatureKey":"ZQJqtJnLseQvg5zXr2O7q+y058uVtLzIn8IWGjgE2Eg=","accountSignature":"0KvtkRmWQ/QFJ0kjYlAyKNEEkQqcHd7/Id4U0/xtYCvbori6Qu81rSzPf8qlcYYxiF+gcXqOCh87tx3oVE4TAg==","deviceSignature":"hUlkuWivBCgZUbexTRez1vmfa1wW8GgVnzWAOEpTr1y5Ik5t47zalID9J6dKAb3ASDrkCx0jb6l5ds6hOxGfgw=="},"me":{"id":"6288292081326:36@s.whatsapp.net","lid":"195279361941673:36@lid","name":"𝓐"},"signalIdentities":[{"identifier":{"name":"195279361941673:36@lid","deviceId":0},"identifierKey":{"type":"Buffer","data":"BWUCarSZy7HkL4Oc169ju6vstOfLlbS8yJ/CFho4BNhI"}}],"platform":"android","routingInfo":{"type":"Buffer","data":"CA0IBQgS"},"lastAccountSyncTimestamp":1781079216,"myAppStateKeyId":"AAAAADBi"}